pysdk/__init__.py
pysdk/typing_extensions.py
pysdk/pyminizip.cpython-39-aarch64-linux-gnu.so
pysdk/adv_math/__init__.py
pysdk/adv_math/arithmetic.py
pysdk/disttools/__init__.py
pysdk/list/read.cpython-39-aarch64-linux-gnu.so
pysdk/list/__init__.py
pysdk/list/count.cpython-39-aarch64-linux-gnu.so
pysdk/list/write.cpython-39-aarch64-linux-gnu.so
pysdk/list/for_each.cpython-39-aarch64-linux-gnu.so
pysdk/list/strutils/__init__.py
pysdk/list/strutils/to_list.cpython-39-aarch64-linux-gnu.so
pysdk/math/__init__.py
pysdk/math/prime.cpython-39-aarch64-linux-gnu.so
pysdk/math/gcd.cpython-39-aarch64-linux-gnu.so
pysdk/dict/read.cpython-39-aarch64-linux-gnu.so
pysdk/dict/__init__.py
pysdk/dict/write.cpython-39-aarch64-linux-gnu.so
pl_python_sdk_full-0.5b1.dist-info/top_level.txt
pl_python_sdk_full-0.5b1.dist-info/METADATA
pl_python_sdk_full-0.5b1.dist-info/LICENSE
pl_python_sdk_full-0.5b1.dist-info/RECORD
pl_python_sdk_full-0.5b1.dist-info/WHEEL
